cotary/__init__.py
cotary/checksum.py
cotary/config.py
cotary/cotary.py
cotary/publisher.py
cotary-0.1.1.dist-info/LICENSE
cotary-0.1.1.dist-info/METADATA
cotary-0.1.1.dist-info/WHEEL
cotary-0.1.1.dist-info/entry_points.txt
cotary-0.1.1.dist-info/top_level.txt
cotary-0.1.1.dist-info/RECORD
