Metadata-Version: 2.1
Name: cotary
Version: 0.1.1
Summary: Prove a file currently exists without disclosing it's content.
Home-page: https://github.com/wchresta/cotary
Author: Wanja Chresta
Author-email: wanja.hs@chrummibei.ch
License: LICENSE
Project-URL: Source Code, https://github.com/wchresta/cotary
Project-URL: Issues, https://github.com/wchresta/cotary/issues
Platform: UNKNOWN
Classifier: Programming Language :: Python :: 3
Classifier: Intended Audience :: End Users/Desktop
Classifier: Intended Audience :: Legal Industry
Classifier: Intended Audience :: Science/Research
Classifier: Development Status :: 4 - Beta
Classifier: Environment :: Console
Classifier: License :: OSI Approved :: GNU General Public License v3 or later (GPLv3+)
Classifier: Operating System :: OS Independent
Classifier: Programming Language :: Python :: 3 :: Only
Classifier: Topic :: Security :: Cryptography
Classifier: Topic :: Utilities
Requires-Python: >=3
Requires-Dist: python-twitter (>=3.0)
Requires-Dist: pyyaml (>=3.0)
